tzfzf/__init__.py
tzfzf/cli.py
tzfzf/output/__init__.py
tzfzf/output/compare.py
tzfzf/smart/__init__.py
tzfzf/smart/exceptions.py
tzfzf/smart/math.py
tzfzf/smart/parser.py
tzfzf/smart/tzinfo.py
tzfzf-0.1.2a2.dist-info/LICENSE
tzfzf-0.1.2a2.dist-info/METADATA
tzfzf-0.1.2a2.dist-info/WHEEL
tzfzf-0.1.2a2.dist-info/entry_points.txt
tzfzf-0.1.2a2.dist-info/top_level.txt
tzfzf-0.1.2a2.dist-info/RECORD
