Metadata-Version: 2.1
Name: tzfzf
Version: 0.1.2a2
Summary: a terminal CLI / API for quick cross-timezone lookups
Home-page: https://github.com/wrynegade/tzfzf
Author: yage
Author-email: yage@yage.io
License: MIT
Platform: UNKNOWN
Classifier: Programming Language :: Python :: 3 :: Only
License-File: LICENSE
Requires-Dist: python-dateutil
Requires-Dist: pytz
Requires-Dist: rich
